tempiny/__init__.py
tempiny-1.4.dist-info/licenses/LICENSE.txt
tempiny-1.4.dist-info/METADATA
tempiny-1.4.dist-info/WHEEL
tempiny-1.4.dist-info/top_level.txt
tempiny-1.4.dist-info/RECORD
