Metadata-Version: 2.4
Name: tempiny
Version: 1.4
Author-email: Léo Flaventin Hauchecorne <hl037.prog@gmail.com>
License: LGPL-2.1-or-later
Classifier: Programming Language :: Python :: 3
Requires-Python: >=3.7
License-File: LICENSE.txt
Dynamic: license-file
